tesm/main.py
tesm-0.1.4.dist-info/LICENSE
tesm-0.1.4.dist-info/WHEEL
tesm-0.1.4.dist-info/METADATA
tesm-0.1.4.dist-info/RECORD
