Metadata-Version: 2.1
Name: tesm
Version: 0.1.4
Summary: Pseudo-assembly programming-like language
License: Unlicense
Author: Ruthenic
Author-email: mdrakea3@tutanota.com
Requires-Python: >=3.8,<4.0
Classifier: License :: Other/Proprietary License
Classifier: Programming Language :: Python :: 3
Classifier: Programming Language :: Python :: 3.8
Classifier: Programming Language :: Python :: 3.9
